yl/__init__.py
yl-0.0.6.dist-info/licenses/LICENSE
yl-0.0.6.dist-info/METADATA
yl-0.0.6.dist-info/WHEEL
yl-0.0.6.dist-info/top_level.txt
yl-0.0.6.dist-info/RECORD
