Metadata-Version: 2.4
Name: yl
Version: 0.0.6
Summary: Get dictionaries from other objects
Home-page: https://github.com/t-c-w/yl
Author: Thor Whalen
License: apache-2.0
Platform: any
License-File: LICENSE
Dynamic: license-file
